cherrybone/__init__.py
cherrybone/cherrybone.py
cherrybone-0.0.5b0.dist-info/LICENSE
cherrybone-0.0.5b0.dist-info/METADATA
cherrybone-0.0.5b0.dist-info/WHEEL
cherrybone-0.0.5b0.dist-info/top_level.txt
cherrybone-0.0.5b0.dist-info/RECORD
